LICENSE
README.md
setup.py
shotp/__main__.py
shotp/typehint.py
shotp.egg-info/PKG-INFO
shotp.egg-info/SOURCES.txt
shotp.egg-info/dependency_links.txt
shotp.egg-info/requires.txt
shotp.egg-info/top_level.txt