Metadata-Version: 2.1
Name: shotp
Version: 0.0.0a1.post1
Summary: A command line interface that implements 2FA apps' functionality.
Home-page: UNKNOWN
License: UNKNOWN
Keywords: otp,2fa
Platform: UNKNOWN
Classifier: Development Status :: 2 - Pre-Alpha
Classifier: Intended Audience :: Developers
Classifier: Operating System :: Microsoft :: Windows :: Windows 10
License-File: LICENSE
